main.py
mseep_zerodha_mcp-0.1.1.dist-info/licenses/LICENSE
mseep_zerodha_mcp-0.1.1.dist-info/METADATA
mseep_zerodha_mcp-0.1.1.dist-info/WHEEL
mseep_zerodha_mcp-0.1.1.dist-info/entry_points.txt
mseep_zerodha_mcp-0.1.1.dist-info/top_level.txt
mseep_zerodha_mcp-0.1.1.dist-info/RECORD
