Metadata-Version: 2.4
Name: mseep-zerodha-mcp
Version: 0.1.1
Summary: Add your description here
Author-email: mseep <support@skydeck.ai>
Requires-Python: >=3.13
License-File: LICENSE
Requires-Dist: fastapi>=0.115.11
Requires-Dist: httpx>=0.28.1
Requires-Dist: kiteconnect>=5.0.1
Requires-Dist: mcp[cli]>=1.3.0
Requires-Dist: python-dotenv>=1.0.1
Requires-Dist: uvicorn>=0.34.0
Dynamic: license-file
